moln/storage.py
moln-0.0.1a1.dist-info/METADATA
moln-0.0.1a1.dist-info/WHEEL
moln-0.0.1a1.dist-info/top_level.txt
moln-0.0.1a1.dist-info/RECORD
