Metadata-Version: 2.1
Name: moln
Version: 0.0.1a1
Summary: Stupid, simple Azure client library built for the rest of us
Home-page: https://github.com/johanste/moln
Author: Johan Stenberg
Author-email: johan.stenberg@microsoft.com
License: UNKNOWN
Platform: UNKNOWN
Classifier: Development Status :: 2 - Pre-Alpha
Classifier: Programming Language :: Python :: 3
Classifier: License :: OSI Approved :: MIT License
Classifier: Operating System :: OS Independent
Requires-Python: >=3.6
Requires-Dist: azure-storage-blob (<13.0.0,>=12.0.0)
Requires-Dist: azure-identity (<2.0.0,>=1.0.0)
